README.md
setup.py
qutie/__init__.py
qutie/action.py
qutie/application.py
qutie/button.py
qutie/checkbox.py
qutie/combobox.py
qutie/dialog.py
qutie/frame.py
qutie/groupbox.py
qutie/icon.py
qutie/label.py
qutie/layout.py
qutie/list.py
qutie/mainwindow.py
qutie/menu.py
qutie/menubar.py
qutie/messagebox.py
qutie/mixins.py
qutie/number.py
qutie/object.py
qutie/pixmap.py
qutie/progressbar.py
qutie/qt.py
qutie/qutie.py
qutie/scrollarea.py
qutie/settings.py
qutie/splitter.py
qutie/stack.py
qutie/table.py
qutie/tabs.py
qutie/text.py
qutie/textarea.py
qutie/timer.py
qutie/toolbar.py
qutie/tree.py
qutie/widget.py
qutie/worker.py
qutie.egg-info/PKG-INFO
qutie.egg-info/SOURCES.txt
qutie.egg-info/dependency_links.txt
qutie.egg-info/requires.txt
qutie.egg-info/top_level.txt