Metadata-Version: 2.1
Name: qutie
Version: 1.7.0
Summary: Yet another pythonic UI library using PyQt5
Home-page: https://github.com/arnobaer/qutie
Author: Bernhard Arnold
Author-email: bernhard.arnold@oeaw.ac.at
License: GPLv3
Platform: UNKNOWN
Classifier: Development Status :: 3 - Alpha
Classifier: Intended Audience :: Developers
Classifier: Programming Language :: Python :: 3
